{"name":"信息系统开发基础","postlist":[{"title":"笔记-信息系统开发基础-uml-uml类图关系","slug":"项目管理学习笔记-1-信息系统开发基础-笔记-信息系统开发基础-uml-uml图例关系","date":"2020-04-25T14:03:25.000Z","updated":"2020-10-31T13:56:35.000Z","comments":true,"path":"api/articles/项目管理学习笔记-1-信息系统开发基础-笔记-信息系统开发基础-uml-uml图例关系.json","excerpt":null,"keywords":null,"cover":"https://i.loli.net/2020/04/25/mNuJoEvWk21hI6K.png","content":null,"raw":null,"categories":[{"name":"信息系统项目管理师","path":"api/categories/信息系统项目管理师.json"},{"name":"信息系统开发基础","path":"api/categories/信息系统开发基础.json"}],"tags":[{"name":"信息系统开发基础","path":"api/tags/信息系统开发基础.json"},{"name":"uml","path":"api/tags/uml.json"}]},{"title":"笔记整理-信息系统开发基础-uml","slug":"项目管理学习笔记-1-信息系统开发基础-笔记-信息系统开发基础-uml","date":"2020-04-25T13:50:02.000Z","updated":"2020-10-31T13:58:35.000Z","comments":true,"path":"api/articles/项目管理学习笔记-1-信息系统开发基础-笔记-信息系统开发基础-uml.json","excerpt":null,"keywords":null,"cover":"https://i.loli.net/2020/04/25/tNzxd6Kio9TrByp.png","content":null,"raw":null,"categories":[{"name":"信息系统项目管理师","path":"api/categories/信息系统项目管理师.json"},{"name":"信息系统开发基础","path":"api/categories/信息系统开发基础.json"}],"tags":[{"name":"信息系统开发基础","path":"api/tags/信息系统开发基础.json"},{"name":"uml","path":"api/tags/uml.json"}]},{"title":"笔记-信息系统开发基础-信息系统开发方法","slug":"项目管理学习笔记-1-信息系统开发基础-笔记-信息系统开发基础-信息系统开发方法","date":"2020-04-23T15:01:23.000Z","updated":"2020-10-31T06:46:07.000Z","comments":true,"path":"api/articles/项目管理学习笔记-1-信息系统开发基础-笔记-信息系统开发基础-信息系统开发方法.json","excerpt":null,"keywords":null,"cover":null,"content":null,"raw":null,"categories":[{"name":"信息系统项目管理师","path":"api/categories/信息系统项目管理师.json"},{"name":"信息系统开发基础","path":"api/categories/信息系统开发基础.json"}],"tags":[{"name":"信息系统开发基础","path":"api/tags/信息系统开发基础.json"},{"name":"软件开发模型","path":"api/tags/软件开发模型.json"},{"name":"信息系统开发","path":"api/tags/信息系统开发.json"}]},{"title":"笔记-信息系统开发基础-信息系统开发模型","slug":"项目管理学习笔记-1-信息系统开发基础-笔记-信息系统开发基础-信息系统开发模型","date":"2020-10-31T05:42:04.000Z","updated":"2020-10-31T05:47:02.000Z","comments":true,"path":"api/articles/项目管理学习笔记-1-信息系统开发基础-笔记-信息系统开发基础-信息系统开发模型.json","excerpt":null,"keywords":null,"cover":null,"content":null,"raw":null,"categories":[{"name":"信息系统项目管理师","path":"api/categories/信息系统项目管理师.json"},{"name":"软件开发模型","path":"api/categories/软件开发模型.json"}],"tags":[{"name":"信息系统开发基础","path":"api/tags/信息系统开发基础.json"},{"name":"软件开发模型","path":"api/tags/软件开发模型.json"},{"name":"瀑布模型","path":"api/tags/瀑布模型.json"},{"name":"V模型","path":"api/tags/V模型.json"},{"name":"喷泉模型","path":"api/tags/喷泉模型.json"},{"name":"螺旋模型","path":"api/tags/螺旋模型.json"},{"name":"统一过程","path":"api/tags/统一过程.json"},{"name":"增量","path":"api/tags/增量.json"},{"name":"迭代模型","path":"api/tags/迭代模型.json"}]},{"title":"笔记-信息系统开发基础-信息系统生命周期","slug":"项目管理学习笔记-1-信息系统开发基础-笔记-信息系统开发基础-信息系统生命周期","date":"2020-04-26T14:49:51.000Z","updated":"2020-11-28T13:12:03.358Z","comments":true,"path":"api/articles/项目管理学习笔记-1-信息系统开发基础-笔记-信息系统开发基础-信息系统生命周期.json","excerpt":null,"keywords":null,"cover":null,"content":null,"raw":null,"categories":[{"name":"信息系统项目管理师","path":"api/categories/信息系统项目管理师.json"},{"name":"信息系统开发基础","path":"api/categories/信息系统开发基础.json"}],"tags":[{"name":"信息系统开发基础","path":"api/tags/信息系统开发基础.json"},{"name":"生命周期","path":"api/tags/生命周期.json"}]},{"title":"笔记-信息系统开发基础-信息系统规划方法-大型新信息系统特征/企业系统规划步骤","slug":"项目管理学习笔记-1-信息系统开发基础-笔记-信息系统开发基础-信息系统规划方法-企业系统规划步骤","date":"2020-04-26T14:29:22.000Z","updated":"2020-10-31T05:39:04.000Z","comments":true,"path":"api/articles/项目管理学习笔记-1-信息系统开发基础-笔记-信息系统开发基础-信息系统规划方法-企业系统规划步骤.json","excerpt":null,"keywords":null,"cover":"https://i.loli.net/2020/04/26/wSckF36A52Nlv8t.png","content":null,"raw":null,"categories":[{"name":"信息系统项目管理师","path":"api/categories/信息系统项目管理师.json"},{"name":"信息系统开发基础","path":"api/categories/信息系统开发基础.json"}],"tags":[{"name":"信息系统开发基础","path":"api/tags/信息系统开发基础.json"},{"name":"大型信息系统","path":"api/tags/大型信息系统.json"},{"name":"BSP","path":"api/tags/BSP.json"},{"name":"企业系统规划","path":"api/tags/企业系统规划.json"},{"name":"R/D矩阵","path":"api/tags/R/D矩阵.json"},{"name":"P/O矩阵","path":"api/tags/P/O矩阵.json"},{"name":"C/U矩阵","path":"api/tags/C/U矩阵.json"}]},{"title":"笔记-信息系统开发基础-架构设计-软件体系结构评估方式","slug":"项目管理学习笔记-1-信息系统开发基础-笔记-信息系统开发基础-架构设计-软件体系结构评估方式","date":"2020-10-31T06:27:16.000Z","updated":"2020-10-31T06:28:27.000Z","comments":true,"path":"api/articles/项目管理学习笔记-1-信息系统开发基础-笔记-信息系统开发基础-架构设计-软件体系结构评估方式.json","excerpt":null,"keywords":null,"cover":null,"content":null,"raw":null,"categories":[{"name":"信息系统项目管理师","path":"api/categories/信息系统项目管理师.json"},{"name":"信息系统开发基础","path":"api/categories/信息系统开发基础.json"}],"tags":[{"name":"信息系统开发基础","path":"api/tags/信息系统开发基础.json"},{"name":"架构设计","path":"api/tags/架构设计.json"},{"name":"软件体系结构评估方式","path":"api/tags/软件体系结构评估方式.json"}]},{"title":"笔记-信息系统开发基础-架构设计-软件架构主要职责","slug":"项目管理学习笔记-1-信息系统开发基础-笔记-信息系统开发基础-架构设计-软件架构主要职责","date":"2020-10-31T06:34:39.000Z","updated":"2020-10-31T06:36:08.000Z","comments":true,"path":"api/articles/项目管理学习笔记-1-信息系统开发基础-笔记-信息系统开发基础-架构设计-软件架构主要职责.json","excerpt":null,"keywords":null,"cover":null,"content":null,"raw":null,"categories":[{"name":"信息系统项目管理师","path":"api/categories/信息系统项目管理师.json"},{"name":"信息系统开发基础","path":"api/categories/信息系统开发基础.json"}],"tags":[{"name":"信息系统开发基础","path":"api/tags/信息系统开发基础.json"},{"name":"架构设计","path":"api/tags/架构设计.json"},{"name":"软件架构主要职责","path":"api/tags/软件架构主要职责.json"}]},{"title":"笔记-信息系统开发基础-架构设计-软件架构风格","slug":"项目管理学习笔记-1-信息系统开发基础-笔记-信息系统开发基础-架构设计-软件架构风格","date":"2020-10-31T06:44:21.000Z","updated":"2020-10-31T06:46:18.000Z","comments":true,"path":"api/articles/项目管理学习笔记-1-信息系统开发基础-笔记-信息系统开发基础-架构设计-软件架构风格.json","excerpt":null,"keywords":null,"cover":null,"content":null,"raw":null,"categories":[{"name":"信息系统项目管理师","path":"api/categories/信息系统项目管理师.json"},{"name":"信息系统开发基础","path":"api/categories/信息系统开发基础.json"}],"tags":[{"name":"信息系统开发基础","path":"api/tags/信息系统开发基础.json"},{"name":"架构设计","path":"api/tags/架构设计.json"},{"name":"软件架构风格","path":"api/tags/软件架构风格.json"}]},{"title":"笔记-信息系统开发基础-架构设计-软件系统架构视图","slug":"项目管理学习笔记-1-信息系统开发基础-笔记-信息系统开发基础-架构设计-软件系统架构视图","date":"2020-10-31T06:29:16.000Z","updated":"2020-10-31T06:41:50.000Z","comments":true,"path":"api/articles/项目管理学习笔记-1-信息系统开发基础-笔记-信息系统开发基础-架构设计-软件系统架构视图.json","excerpt":null,"keywords":null,"cover":null,"content":null,"raw":null,"categories":[{"name":"信息系统项目管理师","path":"api/categories/信息系统项目管理师.json"},{"name":"信息系统开发基础","path":"api/categories/信息系统开发基础.json"}],"tags":[{"name":"信息系统开发基础","path":"api/tags/信息系统开发基础.json"},{"name":"架构设计","path":"api/tags/架构设计.json"},{"name":"软件系统架构视图","path":"api/tags/软件系统架构视图.json"}]}]}