{"name":"收集需求","postlist":[{"title":"笔记-项目范围管理-收集需求过程的工具方法","slug":"项目管理学习笔记-10-项目范围管理-笔记-项目范围管理-收集需求过程的工具方法","date":"2020-08-29T05:48:33.000Z","updated":"2020-10-22T15:28:17.000Z","comments":true,"path":"api/articles/项目管理学习笔记-10-项目范围管理-笔记-项目范围管理-收集需求过程的工具方法.json","excerpt":null,"keywords":null,"cover":null,"content":null,"raw":null,"categories":[{"name":"信息系统项目管理师","path":"api/categories/信息系统项目管理师.json"},{"name":"项目范围管理","path":"api/categories/项目范围管理.json"}],"tags":[{"name":"收集需求","path":"api/tags/收集需求.json"},{"name":"需求开发","path":"api/tags/需求开发.json"}]}]}